easylogger/__init__.py
easylogger/easylogger.py
easylogger/test.py
easylogger-2.1.0.dist-info/METADATA
easylogger-2.1.0.dist-info/RECORD
easylogger-2.1.0.dist-info/WHEEL
easylogger-2.1.0.dist-info/top_level.txt
