Metadata-Version: 2.1
Name: easylogger
Version: 2.1.0
Summary: A tiny logger , make life a little easier
Home-page: https://gitlab.com/public-aarmn-simple/easylogger
Author: AARMN
Author-email: aarmn80@gmail.com
License: UNKNOWN
Platform: UNKNOWN
Classifier: Programming Language :: Python :: 3
Classifier: License :: OSI Approved :: MIT License
Classifier: Operating System :: OS Independent
